simplecalcZ/__init__.py
simplecalcZ/core.py
simplecalcz-0.1.0.dist-info/METADATA
simplecalcz-0.1.0.dist-info/WHEEL
simplecalcz-0.1.0.dist-info/top_level.txt
simplecalcz-0.1.0.dist-info/RECORD
