Metadata-Version: 2.4
Name: simplecalcZ
Version: 0.1.0
Summary: A simple calculator package with basic math functions.
Author: EDharmawan
Author-email: egadharmawan53@email.com
Classifier: Programming Language :: Python :: 3
Classifier: Operating System :: OS Independent
Requires-Python: >=3.6
Dynamic: author
Dynamic: author-email
Dynamic: classifier
Dynamic: requires-python
Dynamic: summary
